[
{"t":1783340456,"temp":25.9,"hum":74,"lux":5},
{"t":1783344336,"temp":25.9,"hum":76,"lux":5},
{"t":1783349295,"temp":25.7,"hum":75,"lux":1},
{"t":1783354463,"temp":25.5,"hum":75,"lux":1},
{"t":1783358337,"temp":25.2,"hum":72,"lux":1},
{"t":1783361945,"temp":24,"hum":68,"lux":1},
{"t":1783365064,"temp":24.5,"hum":72,"lux":1},
{"t":1783368022,"temp":23.8,"hum":70,"lux":1},
{"t":1783370741,"temp":24.2,"hum":72,"lux":1},
{"t":1783372859,"temp":24.2,"hum":72,"lux":1},
{"t":1783375325,"temp":24.4,"hum":73,"lux":1},
{"t":1783377409,"temp":24.4,"hum":73,"lux":1},
{"t":1783379638,"temp":24.6,"hum":74,"lux":1},
{"t":1783381335,"temp":24.6,"hum":74,"lux":2},
{"t":1783383264,"temp":24.8,"hum":74,"lux":1},
{"t":1783386343,"temp":25,"hum":74,"lux":11},
{"t":1783389740,"temp":25,"hum":74,"lux":10},
{"t":1783395261,"temp":25.2,"hum":74,"lux":11},
{"t":1783395919,"temp":25.2,"hum":74,"lux":11},
{"t":1783396849,"temp":25,"hum":73,"lux":11},
{"t":1783397717,"temp":25,"hum":73,"lux":3},
{"t":1783398640,"temp":25.2,"hum":74,"lux":3},
{"t":1783399519,"temp":24.6,"hum":71,"lux":10},
{"t":1783400444,"temp":24.8,"hum":72,"lux":9},
{"t":1783401316,"temp":25,"hum":73,"lux":10},
{"t":1783402241,"temp":25,"hum":73,"lux":10},
{"t":1783403117,"temp":25.2,"hum":74,"lux":10},
{"t":1783404048,"temp":25.2,"hum":74,"lux":8},
{"t":1783404918,"temp":25.2,"hum":74,"lux":6},
{"t":1783405843,"temp":25.2,"hum":74,"lux":6},
{"t":1783406716,"temp":25.2,"hum":74,"lux":5},
{"t":1783407653,"temp":25.2,"hum":74,"lux":5},
{"t":1783408519,"temp":25.2,"hum":74,"lux":6},
{"t":1783409442,"temp":25.2,"hum":74,"lux":7},
{"t":1783410319,"temp":25.2,"hum":74,"lux":6},
{"t":1783411250,"temp":25.2,"hum":72,"lux":5},
{"t":1783412118,"temp":25.2,"hum":72,"lux":4},
{"t":1783413042,"temp":25.2,"hum":72,"lux":3},
{"t":1783413917,"temp":25.2,"hum":72,"lux":3},
{"t":1783414850,"temp":25.2,"hum":72,"lux":2},
{"t":1783415719,"temp":25.2,"hum":72,"lux":1},
{"t":1783416640,"temp":25.2,"hum":72,"lux":1},
{"t":1783417517,"temp":25.4,"hum":73,"lux":9},
{"t":1783418447,"temp":25.4,"hum":73,"lux":1},
{"t":1783419321,"temp":25.4,"hum":73,"lux":1},
{"t":1783420241,"temp":25.4,"hum":73,"lux":1},
{"t":1783421117,"temp":25.2,"hum":72,"lux":1},
{"t":1783422052,"temp":25.2,"hum":72,"lux":1},
{"t":1783422918,"temp":25.2,"hum":72,"lux":1},
{"t":1783423844,"temp":25.2,"hum":72,"lux":1},
{"t":1783424718,"temp":25.2,"hum":72,"lux":5},
{"t":1783425653,"temp":25,"hum":71,"lux":6},
{"t":1783426518,"temp":24.9,"hum":69,"lux":1},
{"t":1783427446,"temp":25,"hum":71,"lux":6},
{"t":1783428318,"temp":25,"hum":71,"lux":5},
{"t":1783429250,"temp":25.2,"hum":72,"lux":5},
{"t":1783430118,"temp":25.3,"hum":74,"lux":5},
{"t":1783431045,"temp":25.3,"hum":74,"lux":5},
{"t":1783431923,"temp":25.3,"hum":74,"lux":5},
{"t":1783432853,"temp":25.3,"hum":74,"lux":1},
{"t":1783433720,"temp":25.3,"hum":74,"lux":1},
{"t":1783434654,"temp":25.3,"hum":74,"lux":1},
{"t":1783435521,"temp":25.3,"hum":74,"lux":1},
{"t":1783436457,"temp":25.3,"hum":74,"lux":1},
{"t":1783437318,"temp":25.3,"hum":74,"lux":1},
{"t":1783438246,"temp":25.3,"hum":74,"lux":1},
{"t":1783439120,"temp":25.3,"hum":74,"lux":1},
{"t":1783440049,"temp":25.3,"hum":74,"lux":1},
{"t":1783440919,"temp":25.3,"hum":74,"lux":1},
{"t":1783441847,"temp":25.3,"hum":74,"lux":1},
{"t":1783442718,"temp":25.3,"hum":74,"lux":1},
{"t":1783443653,"temp":25.3,"hum":74,"lux":1},
{"t":1783444519,"temp":25.3,"hum":74,"lux":1},
{"t":1783445440,"temp":25.3,"hum":74,"lux":1},
{"t":1783446320,"temp":25.3,"hum":74,"lux":1},
{"t":1783447248,"temp":25.3,"hum":74,"lux":1},
{"t":1783448119,"temp":25.1,"hum":75,"lux":1},
{"t":1783449046,"temp":25.1,"hum":75,"lux":1},
{"t":1783449917,"temp":25.1,"hum":75,"lux":1},
{"t":1783450861,"temp":25.1,"hum":75,"lux":1},
{"t":1783451719,"temp":25.1,"hum":75,"lux":1},
{"t":1783452644,"temp":25.1,"hum":75,"lux":1},
{"t":1783453518,"temp":25.1,"hum":75,"lux":1},
{"t":1783454447,"temp":24.9,"hum":75,"lux":1},
{"t":1783455317,"temp":24.9,"hum":75,"lux":1},
{"t":1783456250,"temp":24.9,"hum":75,"lux":1},
{"t":1783457118,"temp":24.9,"hum":75,"lux":1},
{"t":1783458054,"temp":24.9,"hum":75,"lux":1},
{"t":1783458918,"temp":24.9,"hum":75,"lux":1},
{"t":1783459845,"temp":24.9,"hum":75,"lux":2},
{"t":1783460717,"temp":24.9,"hum":75,"lux":2},
{"t":1783461646,"temp":24.9,"hum":75,"lux":2},
{"t":1783462519,"temp":24.9,"hum":75,"lux":2},
{"t":1783463446,"temp":24.9,"hum":75,"lux":2},
{"t":1783464317,"temp":24.9,"hum":75,"lux":2},
{"t":1783465253,"temp":24.9,"hum":75,"lux":2},
{"t":1783466117,"temp":24.9,"hum":75,"lux":2},
{"t":1783467044,"temp":24.9,"hum":75,"lux":2},
{"t":1783467920,"temp":24.9,"hum":75,"lux":2},
{"t":1783468851,"temp":24.9,"hum":75,"lux":2},
{"t":1783469718,"temp":25,"hum":73,"lux":2},
{"t":1783470642,"temp":25,"hum":73,"lux":2},
{"t":1783471519,"temp":25,"hum":73,"lux":2},
{"t":1783472450,"temp":25,"hum":73,"lux":2},
{"t":1783473318,"temp":25,"hum":73,"lux":2},
{"t":1783474243,"temp":25.2,"hum":73,"lux":2},
{"t":1783475118,"temp":25.2,"hum":73,"lux":1},
{"t":1783476046,"temp":25.2,"hum":73,"lux":1},
{"t":1783476920,"temp":25.2,"hum":73,"lux":1},
{"t":1783477843,"temp":25.2,"hum":73,"lux":1},
{"t":1783478716,"temp":25.2,"hum":73,"lux":1},
{"t":1783479648,"temp":25.4,"hum":72,"lux":1},
{"t":1783480516,"temp":25.4,"hum":72,"lux":1},
{"t":1783481439,"temp":25.4,"hum":72,"lux":1},
{"t":1783482318,"temp":25.4,"hum":72,"lux":1},
{"t":1783483246,"temp":25.6,"hum":72,"lux":1},
{"t":1783484118,"temp":25.6,"hum":72,"lux":1},
{"t":1783485038,"temp":25.6,"hum":72,"lux":1},
{"t":1783485918,"temp":25.8,"hum":72,"lux":2},
{"t":1783486848,"temp":25.8,"hum":72,"lux":2},
{"t":1783487716,"temp":25.8,"hum":72,"lux":2},
{"t":1783488642,"temp":25.8,"hum":72,"lux":2},
{"t":1783489516,"temp":26,"hum":72,"lux":2},
{"t":1783490448,"temp":26,"hum":72,"lux":1},
{"t":1783491318,"temp":26,"hum":72,"lux":1},
{"t":1783492245,"temp":26,"hum":72,"lux":1},
{"t":1783493120,"temp":26,"hum":72,"lux":1},
{"t":1783494052,"temp":26.2,"hum":72,"lux":1},
{"t":1783494919,"temp":26.2,"hum":72,"lux":1},
{"t":1783495844,"temp":26.2,"hum":72,"lux":1},
{"t":1783496719,"temp":26.2,"hum":72,"lux":1},
{"t":1783497651,"temp":26.2,"hum":72,"lux":1},
{"t":1783498518,"temp":26.2,"hum":72,"lux":1},
{"t":1783499447,"temp":26.2,"hum":72,"lux":3},
{"t":1783500317,"temp":26.2,"hum":72,"lux":3},
{"t":1783501252,"temp":26.4,"hum":72,"lux":8},
{"t":1783502117,"temp":26.4,"hum":72,"lux":7},
{"t":1783503048,"temp":26.4,"hum":72,"lux":6},
{"t":1783503919,"temp":26.6,"hum":72,"lux":1},
{"t":1783504851,"temp":26.4,"hum":72,"lux":1},
{"t":1783505716,"temp":26.4,"hum":72,"lux":1},
{"t":1783506648,"temp":26.6,"hum":72,"lux":5},
{"t":1783507518,"temp":26.6,"hum":72,"lux":5},
{"t":1783508452,"temp":26.6,"hum":72,"lux":5},
{"t":1783509320,"temp":26.6,"hum":72,"lux":5},
{"t":1783510259,"temp":26.6,"hum":72,"lux":5},
{"t":1783511119,"temp":26.4,"hum":72,"lux":5},
{"t":1783512059,"temp":26.4,"hum":72,"lux":5},
{"t":1783512932,"temp":26.2,"hum":72,"lux":5},
{"t":1783513847,"temp":26,"hum":72,"lux":5},
{"t":1783514720,"temp":25.8,"hum":71,"lux":5},
{"t":1783515654,"temp":26,"hum":72,"lux":1},
{"t":1783516527,"temp":25.7,"hum":71,"lux":1},
{"t":1783517451,"temp":25.6,"hum":70,"lux":1},
{"t":1783518340,"temp":25.8,"hum":70,"lux":1},
{"t":1783519268,"temp":26,"hum":71,"lux":1},
{"t":1783520118,"temp":26.1,"hum":73,"lux":1},
{"t":1783521049,"temp":26.1,"hum":73,"lux":1},
{"t":1783521921,"temp":26.1,"hum":73,"lux":1},
{"t":1783522857,"temp":25.9,"hum":73,"lux":1},
{"t":1783523720,"temp":25.9,"hum":73,"lux":1},
{"t":1783524648,"temp":25.9,"hum":73,"lux":1},
{"t":1783525522,"temp":25.9,"hum":73,"lux":1},
{"t":1783526457,"temp":25.9,"hum":73,"lux":5},
{"t":1783527320,"temp":25.9,"hum":73,"lux":5},
{"t":1783528253,"temp":25.9,"hum":73,"lux":1},
{"t":1783529122,"temp":25.9,"hum":73,"lux":5},
{"t":1783530059,"temp":25.6,"hum":72,"lux":1},
{"t":1783530922,"temp":25.8,"hum":73,"lux":1},
{"t":1783531855,"temp":25.8,"hum":73,"lux":1},
{"t":1783532720,"temp":25.8,"hum":73,"lux":1},
{"t":1783533660,"temp":25.8,"hum":73,"lux":1},
{"t":1783534518,"temp":25.8,"hum":73,"lux":1},
{"t":1783535448,"temp":25.8,"hum":73,"lux":1},
{"t":1783536317,"temp":25.8,"hum":73,"lux":1},
{"t":1783537252,"temp":25.8,"hum":73,"lux":1},
{"t":1783538119,"temp":25.8,"hum":73,"lux":1},
{"t":1783539051,"temp":25.8,"hum":73,"lux":1},
{"t":1783539918,"temp":25.8,"hum":73,"lux":1},
{"t":1783540854,"temp":25.8,"hum":73,"lux":1},
{"t":1783541718,"temp":25.6,"hum":74,"lux":1},
{"t":1783542652,"temp":25.6,"hum":74,"lux":1},
{"t":1783543517,"temp":25.6,"hum":74,"lux":1},
{"t":1783544456,"temp":25.6,"hum":74,"lux":2},
{"t":1783545319,"temp":25.6,"hum":74,"lux":2},
{"t":1783546246,"temp":25.6,"hum":74,"lux":2},
{"t":1783547119,"temp":25.6,"hum":74,"lux":2},
{"t":1783548057,"temp":25.6,"hum":74,"lux":11},
{"t":1783548918,"temp":25.8,"hum":75,"lux":12},
{"t":1783549853,"temp":25.8,"hum":75,"lux":12},
{"t":1783550717,"temp":25.8,"hum":75,"lux":12},
{"t":1783551654,"temp":25.8,"hum":75,"lux":12},
{"t":1783552517,"temp":25.8,"hum":75,"lux":12},
{"t":1783553446,"temp":26,"hum":74,"lux":12},
{"t":1783554318,"temp":26,"hum":74,"lux":12}
]
